AUTHORS
COPYING
MANIFEST.in
README
release
setup.py
setuplib.py
inotifyx/__init__.py
inotifyx/binding.c
inotifyx/distinfo.py
inotifyx_py3.egg-info/PKG-INFO
inotifyx_py3.egg-info/SOURCES.txt
inotifyx_py3.egg-info/dependency_links.txt
inotifyx_py3.egg-info/top_level.txt