Metadata-Version: 1.0
Name: inotifyx-py3
Version: 0.3.1
Summary: Simple Linux inotify bindings
Home-page: https://launchpad.net/inotifyx/
Author: Forest Bond
Author-email: forest@forestbond.com
License: UNKNOWN
Platform: UNKNOWN
